setup.py
B_pp/B_pp.py
B_pp/__init__.py
B_pp.egg-info/PKG-INFO
B_pp.egg-info/SOURCES.txt
B_pp.egg-info/dependency_links.txt
B_pp.egg-info/entry_points.txt
B_pp.egg-info/top_level.txt