Metadata-Version: 1.1
Name: B-pp
Version: 1.1
Summary: A code template processor
Home-page: http://github.com/JohnFNovak/B_pp/
Author: John F Novak
Author-email: john.franc.novak@gmail.com
License: Public Domain
Platform: any
Classifier: Programming Language :: Python
Classifier: Development Status :: 5 - Production/Stable
Classifier: Natural Language :: English
Classifier: Environment :: Console
Classifier: License :: Public Domain
Classifier: Operating System :: OS Independent
Classifier: Topic :: Software Development
